starlette_admin_beanie_backend/__init__.py
starlette_admin_beanie_backend/admin.py
starlette_admin_beanie_backend/converters.py
starlette_admin_beanie_backend/exceptions.py
starlette_admin_beanie_backend/helpers.py
starlette_admin_beanie_backend/view.py
starlette_admin_beanie_backend-0.1.1.dist-info/METADATA
starlette_admin_beanie_backend-0.1.1.dist-info/WHEEL
starlette_admin_beanie_backend-0.1.1.dist-info/top_level.txt
starlette_admin_beanie_backend-0.1.1.dist-info/RECORD
