Metadata-Version: 2.4
Name: starlette-admin-beanie-backend
Version: 0.1.1
Summary: Beanie-ODM support for Starlette Admin
Author-email: Arnab Jain <arnab@inocentum.in>
License-Expression: MIT
Project-URL: Homepage, https://github.com/arnabJ/starlette-admin-beanie-backend
Project-URL: Bug Tracker, https://github.com/arnabJ/starlette-admin-beanie-backend/issues
Project-URL: Source, https://github.com/arnabJ/starlette-admin-beanie-backend
Project-URL: Changelog, https://github.com/arnabJ/starlette-admin-beanie-backend/releases
Project-URL: Documentation, https://github.com/arnabJ/starlette-admin-beanie-backend/blob/main/README.md
Classifier: Programming Language :: Python
Classifier: Programming Language :: Python :: 3
Classifier: Programming Language :: Python :: 3 :: Only
Classifier: Programming Language :: Python :: 3.9
Classifier: Programming Language :: Python :: 3.10
Classifier: Programming Language :: Python :: 3.11
Classifier: Programming Language :: Python :: 3.12
Classifier: Programming Language :: Python :: 3.13
Classifier: Intended Audience :: Developers
Classifier: Intended Audience :: Information Technology
Classifier: Intended Audience :: System Administrators
Classifier: Operating System :: OS Independent
Classifier: Topic :: Software Development :: Libraries :: Python Modules
Classifier: Topic :: Internet
Requires-Python: <3.14,>=3.9
Requires-Dist: starlette-admin>=0.15.1
Requires-Dist: beanie>=2.0.0
